pycountsxch/__init__.py
pycountsxch/plotting.py
pycountsxch/pycounts.py
pycountsxch-0.1.3.dist-info/LICENSE
pycountsxch-0.1.3.dist-info/WHEEL
pycountsxch-0.1.3.dist-info/METADATA
pycountsxch-0.1.3.dist-info/RECORD
