Metadata-Version: 2.1
Name: pycountsxch
Version: 0.1.3
Summary: Python package to count text
License: MIT
Author: Charles Xu
Requires-Python: >=3.9
Classifier: License :: OSI Approved :: MIT License
Classifier: Programming Language :: Python :: 3
Classifier: Programming Language :: Python :: 3.9
Classifier: Programming Language :: Python :: 3.10
Requires-Dist: matplotlib (>=3.4.3)
